oapi_parse/__init__.py
oapi_parse/commons/__init__.py
oapi_parse/commons/common_methods.py
oapi_parse/exceptions/__init__.py
oapi_parse/exceptions/oapi_exceptions.py
oapi_parse/extract/__init__.py
oapi_parse/extract/extractor.py
oapi_parse/reader/__init__.py
oapi_parse/reader/oapijson.py
oapi_parse/reader/oapiyml.py
oapi_parse/schema_validate/__init__.py
oapi_parse/schema_validate/schema_validator.py
oapi_parser-1.0.0a0.dist-info/LICENSE
oapi_parser-1.0.0a0.dist-info/METADATA
oapi_parser-1.0.0a0.dist-info/WHEEL
oapi_parser-1.0.0a0.dist-info/top_level.txt
oapi_parser-1.0.0a0.dist-info/RECORD
