Metadata-Version: 2.1
Name: oapi-parser
Version: 1.0.0a0
Summary: A simple Open API parser
Home-page: UNKNOWN
Author: Srikanth_Srigakolapu
Author-email: srikanth.srigakolapu@gmail.com
License: UNKNOWN
Platform: UNKNOWN
Requires-Python: >3.6
Requires-Dist: pyyaml
Requires-Dist: jsonschema
Requires-Dist: pytest
